netbox_custom_objects/__init__.py
netbox_custom_objects/choices.py
netbox_custom_objects/constants.py
netbox_custom_objects/field_types.py
netbox_custom_objects/fields.py
netbox_custom_objects/filtersets.py
netbox_custom_objects/forms.py
netbox_custom_objects/models.py
netbox_custom_objects/navigation.py
netbox_custom_objects/search.py
netbox_custom_objects/tables.py
netbox_custom_objects/template_content.py
netbox_custom_objects/urls.py
netbox_custom_objects/utilities.py
netbox_custom_objects/views.py
netbox_custom_objects/api/__init__.py
netbox_custom_objects/api/serializers.py
netbox_custom_objects/api/urls.py
netbox_custom_objects/api/views.py
netbox_custom_objects/migrations/0001_initial.py
netbox_custom_objects/migrations/0002_customobjecttype_cache_timestamp.py
netbox_custom_objects/migrations/0003_ensure_fk_constraints.py
netbox_custom_objects/migrations/__init__.py
netbox_custom_objects/templates/buttons/custom_objects_delete.html
netbox_custom_objects/templates/netbox_custom_objects/custom_object_bulk_edit.html
netbox_custom_objects/templates/netbox_custom_objects/custom_object_bulk_import.html
netbox_custom_objects/templates/netbox_custom_objects/custom_object_list.html
netbox_custom_objects/templates/netbox_custom_objects/customobject.html
netbox_custom_objects/templates/netbox_custom_objects/customobject_edit.html
netbox_custom_objects/templates/netbox_custom_objects/customobjecttype.html
netbox_custom_objects/templates/netbox_custom_objects/field_delete.html
netbox_custom_objects/templates/netbox_custom_objects/object_journal.html
netbox_custom_objects/templates/netbox_custom_objects/htmx/delete_form.html
netbox_custom_objects/templates/netbox_custom_objects/inc/branch_warning.html
netbox_custom_objects/templatetags/__init__.py
netbox_custom_objects/templatetags/custom_object_buttons.py
netbox_custom_objects/templatetags/custom_object_utils.py
netboxlabs_netbox_custom_objects-0.4.5.dist-info/licenses/LICENSE.md
netboxlabs_netbox_custom_objects-0.4.5.dist-info/METADATA
netboxlabs_netbox_custom_objects-0.4.5.dist-info/WHEEL
netboxlabs_netbox_custom_objects-0.4.5.dist-info/top_level.txt
netboxlabs_netbox_custom_objects-0.4.5.dist-info/RECORD
