Metadata-Version: 2.4
Name: netboxlabs-netbox-custom-objects
Version: 0.4.5
Summary: A plugin to manage custom objects in NetBox
Author-email: NetBox Labs <support@netboxlabs.com>
Maintainer-email: NetBox Labs <support@netboxlabs.com>
License: NetBox Limited Use License 1.0
Project-URL: Homepage, https://netboxlabs.com/
Classifier: Development Status :: 4 - Beta
Classifier: Intended Audience :: Developers
Classifier: Topic :: Software Development :: Build Tools
Classifier: Programming Language :: Python :: 3
Classifier: Programming Language :: Python :: 3 :: Only
Classifier: Programming Language :: Python :: 3.10
Classifier: Programming Language :: Python :: 3.11
Classifier: Programming Language :: Python :: 3.12
Requires-Python: >=3.10
License-File: LICENSE.md
Requires-Dist: Django
Provides-Extra: dev
Requires-Dist: check-manifest; extra == "dev"
Requires-Dist: mkdocs; extra == "dev"
Requires-Dist: mkdocs-material; extra == "dev"
Requires-Dist: ruff; extra == "dev"
Provides-Extra: test
Requires-Dist: coverage; extra == "test"
Requires-Dist: pytest; extra == "test"
Requires-Dist: pytest-cov; extra == "test"
Dynamic: license-file
